fsm_iterator/fsm_iterator.v

module signed_mult (
    output signed [26:0] out,
    input  signed [26:0] a,
    input  signed [26:0] b
);
    // intermediate full bit length
    wire signed [53:0] mult_out;
    assign mult_out = a * b;
    // select bits for 4.23 fixed point
    assign out = {mult_out[53], mult_out[48:23]};
endmodule

module fsm_iterator (
    input reset,
    input clk,
    input in_val,
    output reg in_rdy,

    input signed  [26:0] in_c_r,
    input signed  [26:0] in_c_i,

    output reg signed [$clog2(`ITER_MAX):0] iter_count,
    output escape_condition,
    output reg out_val,
    input out_rdy
);
    // state machine encoding 
    localparam [2:0] IDLE   = 3'b000,
                     CALC_1 = 3'b001,
                     CALC_2 = 3'b010,
                     CALC_3 = 3'b011,
                     DONE   = 3'b100;
                     
    reg [2:0] current_state = IDLE;
    reg [2:0] next_state;

    // internal registers for iterative calculations
    reg signed [26:0] zi, zr, c_r, c_i;
    reg signed [26:0] zr_sq_reg, zi_sq_reg;
    wire signed [26:0] zr_next, zi_next, z_mag_sq;


   // instantiate ONE multiplier 
    reg  signed [26:0] mult_in_a, mult_in_b;
    wire signed [26:0] mult_out;

    signed_mult single_mult(mult_out, mult_in_a, mult_in_b);

    always @(posedge clk) begin
        case (current_state)
            IDLE: begin
                if (in_val) begin
                    c_r <= in_c_r;
                    c_i <= in_c_i;
                    zi <= 27'sd0;
                    zr <= 27'sd0;
                    zr_sq_reg <= 27'sd0;
                    zi_sq_reg <= 27'sd0;
                    iter_count <= 0;
                end
            end
            CALC_1: begin
                zr_sq_reg <= mult_out;
            end
            CALC_2: begin
                zi_sq_reg <= mult_out;
            end
            CALC_3: begin
                zi <= zi_next;
                zr <= zr_next;
                iter_count <= iter_count + 1;
            end
            DONE: begin
                // do nothing
            end
        endcase

        // update state
        if (reset) begin
            current_state <= IDLE;
        end else begin
            current_state <= next_state;
        end
    end

    // next state and output logic
    always @(*) begin
        next_state = current_state;
        in_rdy = 1'b0;
        out_val = 1'b0;

        case (current_state)
            IDLE: begin
                in_rdy = 1'b1;
                if (in_val) begin
                    next_state = CALC_1;
                end
            end
            CALC_1: begin
                next_state = CALC_2;
            end
            CALC_2: begin
                next_state = CALC_3;
            end
            CALC_3: begin
                if (escape_condition) begin
                    next_state = DONE;
                end else begin
                    next_state = CALC_1;
                end
            end
            DONE: begin
                out_val = 1'b1;
                if (out_rdy) begin
                    next_state = IDLE;
                end
            end
        endcase
    end

    // multiplier input mux based on state
    always @(*) begin
        case (current_state)
            CALC_1: begin
                mult_in_a = zr;
                mult_in_b = zr;
            end
            CALC_2: begin
                mult_in_a = zi;
                mult_in_b = zi;
            end
            CALC_3, DONE: begin 
                mult_in_a = zr;
                mult_in_b = zi;
            end
            default: begin
                mult_in_a = 27'sd0;
                mult_in_b = 27'sd0;
            end
        endcase
    end

    // combinational arithmetic
    assign zr_next = zr_sq_reg - zi_sq_reg + c_r;
    assign zi_next = (mult_out <<< 1) + c_i;  
    assign z_mag_sq = zr_sq_reg + zi_sq_reg;

    assign escape_condition = (z_mag_sq > $signed(27'h2000000)) 
                            || (iter_count == `ITER_MAX - 1)
                            || (zi_next > $signed(27'h1000000)) 
                            || (zi_next < $signed(-27'h1000000)) 
                            || (zr_next > $signed(27'h1000000)) 
                            || (zr_next < $signed(-27'h1000000));

endmodule

fsm_iterator/tb_fsm_iterator.v
`timescale 1ns/1ps
`define ITER_MAX 1000

module tb_fsm_iterator;

    // Inputs
    reg reset;
    reg clk;
    reg in_val;
    reg signed [26:0] in_c_r;
    reg signed [26:0] in_c_i;
    reg out_rdy;

    // Outputs
    wire in_rdy;
    wire [$clog2(`ITER_MAX):0] iter_count;
    wire escape_condition;
    wire out_val;

    // Instantiate the Unit Under Test (UUT)
    fsm_iterator uut (
        .reset(reset), 
        .clk(clk), 
        .in_val(in_val), 
        .in_rdy(in_rdy), 
        .in_c_r(in_c_r), 
        .in_c_i(in_c_i), 
        .iter_count(iter_count), 
        .escape_condition(escape_condition), 
        .out_val(out_val), 
        .out_rdy(out_rdy)
    );

    // ---------------------------------------------------------
    // Clock Generation (100 MHz)
    // ---------------------------------------------------------
    initial begin
        clk = 0;
        forever #5 clk = ~clk; 
    end

    // ---------------------------------------------------------
    // Helper Task: Send a coordinate and wait for result
    // ---------------------------------------------------------
    // ---------------------------------------------------------
    // Helper Task: Send a coordinate and wait for result
    // ---------------------------------------------------------
    task test_point;
        input signed [26:0] c_r;
        input signed [26:0] c_i;
        begin
            // 1. Wait until DUT is ready for new data
            while (!in_rdy) @(posedge clk);
            
            // 2. Drive inputs using NON-BLOCKING assignments
            in_c_r <= c_r;
            in_c_i <= c_i;
            in_val <= 1'b1;
            
            // 3. Wait one clock cycle for the handshake to register
            @(posedge clk);
            in_val <= 1'b0; // De-assert using NON-BLOCKING assignment

            // 4. Wait for DUT to finish calculation
            while (!out_val) @(posedge clk);
            
            // 5. Print results (converting Q4.23 back to float for the console)
            $display("Tested C = (%f, %f) | Iterations: %0d | Escaped: %0b", 
                     $itor(c_r) / 8388608.0, 
                     $itor(c_i) / 8388608.0, 
                     iter_count, 
                     escape_condition);
            
            // 6. Acknowledge the output using NON-BLOCKING assignments
            out_rdy <= 1'b1;
            @(posedge clk);
            out_rdy <= 1'b0;
            
            // Add a small gap between tests in the waveform
            repeat(5) @(posedge clk);
        end
    endtask

    // ---------------------------------------------------------
    // Main Test Stimulus
    // ---------------------------------------------------------
    initial begin
        // Setup VCD dumping for GTKWave viewing
        $dumpfile("mandelbrot.vcd");
        $dumpvars(0, tb_fsm_iterator);

        // Initialize Inputs
        reset = 1;
        in_val = 0;
        in_c_r = 0;
        in_c_i = 0;
        out_rdy = 0;

        // Wait 100 ns for global reset to finish
        #100;
        reset = 0;
        repeat(5) @(posedge clk);

        $display("--- Starting Mandelbrot FSM Tests ---");

        // Test Case 1: C = 0 + 0i (Deep inside the set, should hit ITER_MAX)
        // 0 in Q4.23 fixed-point is 27'h0000000
        test_point(27'h0000000, 27'h0000000);

        // Test Case 2: C = -2.0 + 0i (Tip of the tail, should hit ITER_MAX)
        // +2.0 is 27'h1000000. Two's complement for -2.0 is 27'h7000000
        test_point(27'h7000000, 27'h0000000);

        // Test Case 3: C = 1.0 + 1.0i (Outside the set, escapes quickly)
        // +1.0 in Q4.23 fixed-point is 27'h0800000
        test_point(27'h0800000, 27'h0800000);

        // Test Case 4: C = -0.5 + 0.5i (Edge of the main cardioid)
        // +0.5 is 27'h0400000. Two's complement for -0.5 is 27'h7C00000
        test_point(27'h7C00000, 27'h0400000);



        test_point(27'h7F33333, 27'h0533333);
        $display("--- Tests Complete ---");
        $finish;
    end

endmodule

fsm_iterator/mandelbrot.vcd
$date
	Fri Feb 20 17:25:45 2026
$end
$version
	Icarus Verilog
$end
$timescale
	1ps
$end
$scope module tb_fsm_iterator $end
$var wire 1 ! out_val $end
$var wire 11 " iter_count [10:0] $end
$var wire 1 # in_rdy $end
$var wire 1 $ escape_condition $end
$var reg 1 % clk $end
$var reg 27 & in_c_i [26:0] $end
$var reg 27 ' in_c_r [26:0] $end
$var reg 1 ( in_val $end
$var reg 1 ) out_rdy $end
$var reg 1 * reset $end
$scope module uut $end
$var wire 1 % clk $end
$var wire 1 $ escape_condition $end
$var wire 27 + in_c_i [26:0] $end
$var wire 27 , in_c_r [26:0] $end
$var wire 1 ( in_val $end
$var wire 1 ) out_rdy $end
$var wire 1 * reset $end
$var wire 27 - zr_next [26:0] $end
$var wire 27 . zi_next [26:0] $end
$var wire 27 / z_mag_sq [26:0] $end
$var wire 27 0 mult_out [26:0] $end
$var parameter 3 1 CALC_1 $end
$var parameter 3 2 CALC_2 $end
$var parameter 3 3 CALC_3 $end
$var parameter 3 4 DONE $end
$var parameter 3 5 IDLE $end
$var reg 27 6 c_i [26:0] $end
$var reg 27 7 c_r [26:0] $end
$var reg 3 8 current_state [2:0] $end
$var reg 1 # in_rdy $end
$var reg 11 9 iter_count [10:0] $end
$var reg 27 : mult_in_a [26:0] $end
$var reg 27 ; mult_in_b [26:0] $end
$var reg 3 < next_state [2:0] $end
$var reg 1 ! out_val $end
$var reg 27 = zi [26:0] $end
$var reg 27 > zi_sq_reg [26:0] $end
$var reg 27 ? zr [26:0] $end
$var reg 27 @ zr_sq_reg [26:0] $end
$scope module single_mult $end
$var wire 27 A a [26:0] $end
$var wire 27 B b [26:0] $end
$var wire 27 C out [26:0] $end
$var wire 54 D mult_out [53:0] $end
$upscope $end
$upscope $end
$scope task test_point $end
$var reg 27 E c_i [26:0] $end
$var reg 27 F c_r [26:0] $end
$upscope $end
$upscope $end
$enddefinitions $end
$comment Show the parameter values. $end
$dumpall
b0 5
b100 4
b11 3
b10 2
b1 1
$end
#0
$dumpvars
bx F
bx E
b0 D
b0 C
b0 B
b0 A
b0 @
b0 ?
b0 >
b0 =
b0 <
b0 ;
b0 :
bx 9
b0 8
b0 7
b0 6
b0 0
b0 /
b0 .
b0 -
b0 ,
b0 +
1*
0)
0(
b0 '
b0 &
0%
x$
1#
bx "
0!
$end
#5000
1%
#10000
0%
#15000
1%
#20000
0%
#25000
1%
#30000
0%
#35000
1%
#40000
0%
#45000
1%
#50000
0%
#55000
1%
#60000
0%
#65000
1%
#70000
0%
#75000
1%
#80000
0%
#85000
1%
#90000
0%
#95000
1%
#100000
0%
0*
#105000
1%
#110000
0%
#115000
1%
#120000
0%
#125000
1%
#130000
0%
#135000
1%
#140000
0%
#145000
b1 <
1#
1(
b0 E
b0 F
1%
#150000
0%
#155000
0$
b10 <
0#
b1 8
b0 "
b0 9
0(
1%
#160000
0%
#165000
b11 <
b10 8
1%
#170000
0%
#175000
b1 <
b11 8
1%
#180000
0%
#185000
b10 <
b1 8
b1 "
b1 9
1%
#190000
0%
#195000
b11 <
b10 8
1%
#200000
0%
#205000
b1 <
b11 8
1%
#210000
0%
#215000
b10 <
b1 8
b10 "
b10 9
1%
#220000
0%
#225000
b11 <
b10 8
1%
#230000
0%
#235000
b1 <
b11 8
1%
#240000
0%
#245000
b10 <
b1 8
b11 "
b11 9
1%
#250000
0%
#255000
b11 <
b10 8
1%
#260000
0%
#265000
b1 <
b11 8
1%
#270000
0%
#275000
b10 <
b1 8
b100 "
b100 9
1%
#280000
0%
#285000
b11 <
b10 8
1%
#290000
0%
#295000
b1 <
b11 8
1%
#300000
0%
#305000
b10 <
b1 8
b101 "
b101 9
1%
#310000
0%
#315000
b11 <
b10 8
1%
#320000
0%
#325000
b1 <
b11 8
1%
#330000
0%
#335000
b10 <
b1 8
b110 "
b110 9
1%
#340000
0%
#345000
b11 <
b10 8
1%
#350000
0%
#355000
b1 <
b11 8
1%
#360000
0%
#365000
b10 <
b1 8
b111 "
b111 9
1%
#370000
0%
#375000
b11 <
b10 8
1%
#380000
0%
#385000
b1 <
b11 8
1%
#390000
0%
#395000
b10 <
b1 8
b1000 "
b1000 9
1%
#400000
0%
#405000
b11 <
b10 8
1%
#410000
0%
#415000
b1 <
b11 8
1%
#420000
0%
#425000
b10 <
b1 8
b1001 "
b1001 9
1%
#430000
0%
#435000
b11 <
b10 8
1%
#440000
0%
#445000
b1 <
b11 8
1%
#450000
0%
#455000
b10 <
b1 8
b1010 "
b1010 9
1%
#460000
0%
#465000
b11 <
b10 8
1%
#470000
0%
#475000
b1 <
b11 8
1%
#480000
0%
#485000
b10 <
b1 8
b1011 "
b1011 9
1%
#490000
0%
#495000
b11 <
b10 8
1%
#500000
0%
#505000
b1 <
b11 8
1%
#510000
0%
#515000
b10 <
b1 8
b1100 "
b1100 9
1%
#520000
0%
#525000
b11 <
b10 8
1%
#530000
0%
#535000
b1 <
b11 8
1%
#540000
0%
#545000
b10 <
b1 8
b1101 "
b1101 9
1%
#550000
0%
#555000
b11 <
b10 8
1%
#560000
0%
#565000
b1 <
b11 8
1%
#570000
0%
#575000
b10 <
b1 8
b1110 "
b1110 9
1%
#580000
0%
#585000
b11 <
b10 8
1%
#590000
0%
#595000
b1 <
b11 8
1%
#600000
0%
#605000
b10 <
b1 8
b1111 "
b1111 9
1%
#610000
0%
#615000
b11 <
b10 8
1%
#620000
0%
#625000
b1 <
b11 8
1%
#630000
0%
#635000
b10 <
b1 8
b10000 "
b10000 9
1%
#640000
0%
#645000
b11 <
b10 8
1%
#650000
0%
#655000
b1 <
b11 8
1%
#660000
0%
#665000
b10 <
b1 8
b10001 "
b10001 9
1%
#670000
0%
#675000
b11 <
b10 8
1%
#680000
0%
#685000
b1 <
b11 8
1%
#690000
0%
#695000
b10 <
b1 8
b10010 "
b10010 9
1%
#700000
0%
#705000
b11 <
b10 8
1%
#710000
0%
#715000
b1 <
b11 8
1%
#720000
0%
#725000
b10 <
b1 8
b10011 "
b10011 9
1%
#730000
0%
#735000
b11 <
b10 8
1%
#740000
0%
#745000
b1 <
b11 8
1%
#750000
0%
#755000
b10 <
b1 8
b10100 "
b10100 9
1%
#760000
0%
#765000
b11 <
b10 8
1%
#770000
0%
#775000
b1 <
b11 8
1%
#780000
0%
#785000
b10 <
b1 8
b10101 "
b10101 9
1%
#790000
0%
#795000
b11 <
b10 8
1%
#800000
0%
#805000
b1 <
b11 8
1%
#810000
0%
#815000
b10 <
b1 8
b10110 "
b10110 9
1%
#820000
0%
#825000
b11 <
b10 8
1%
#830000
0%
#835000
b1 <
b11 8
1%
#840000
0%
#845000
b10 <
b1 8
b10111 "
b10111 9
1%
#850000
0%
#855000
b11 <
b10 8
1%
#860000
0%
#865000
b1 <
b11 8
1%
#870000
0%
#875000
b10 <
b1 8
b11000 "
b11000 9
1%
#880000
0%
#885000
b11 <
b10 8
1%
#890000
0%
#895000
b1 <
b11 8
1%
#900000
0%
#905000
b10 <
b1 8
b11001 "
b11001 9
1%
#910000
0%
#915000
b11 <
b10 8
1%
#920000
0%
#925000
b1 <
b11 8
1%
#930000
0%
#935000
b10 <
b1 8
b11010 "
b11010 9
1%
#940000
0%
#945000
b11 <
b10 8
1%
#950000
0%
#955000
b1 <
b11 8
1%
#960000
0%
#965000
b10 <
b1 8
b11011 "
b11011 9
1%
#970000
0%
#975000
b11 <
b10 8
1%
#980000
0%
#985000
b1 <
b11 8
1%
#990000
0%
#995000
b10 <
b1 8
b11100 "
b11100 9
1%
#1000000
0%
#1005000
b11 <
b10 8
1%
#1010000
0%
#1015000
b1 <
b11 8
1%
#1020000
0%
#1025000
b10 <
b1 8
b11101 "
b11101 9
1%
#1030000
0%
#1035000
b11 <
b10 8
1%
#1040000
0%
#1045000
b1 <
b11 8
1%
#1050000
0%
#1055000
b10 <
b1 8
b11110 "
b11110 9
1%
#1060000
0%
#1065000
b11 <
b10 8
1%
#1070000
0%
#1075000
b1 <
b11 8
1%
#1080000
0%
#1085000
b10 <
b1 8
b11111 "
b11111 9
1%
#1090000
0%
#1095000
b11 <
b10 8
1%
#1100000
0%
#1105000
b1 <
b11 8
1%
#1110000
0%
#1115000
b10 <
b1 8
b100000 "
b100000 9
1%
#1120000
0%
#1125000
b11 <
b10 8
1%
#1130000
0%
#1135000
b1 <
b11 8
1%
#1140000
0%
#1145000
b10 <
b1 8
b100001 "
b100001 9
1%
#1150000
0%
#1155000
b11 <
b10 8
1%
#1160000
0%
#1165000
b1 <
b11 8
1%
#1170000
0%
#1175000
b10 <
b1 8
b100010 "
b100010 9
1%
#1180000
0%
#1185000
b11 <
b10 8
1%
#1190000
0%
#1195000
b1 <
b11 8
1%
#1200000
0%
#1205000
b10 <
b1 8
b100011 "
b100011 9
1%
#1210000
0%
#1215000
b11 <
b10 8
1%
#1220000
0%
#1225000
b1 <
b11 8
1%
#1230000
0%
#1235000
b10 <
b1 8
b100100 "
b100100 9
1%
#1240000
0%
#1245000
b11 <
b10 8
1%
#1250000
0%
#1255000
b1 <
b11 8
1%
#1260000
0%
#1265000
b10 <
b1 8
b100101 "
b100101 9
1%
#1270000
0%
#1275000
b11 <
b10 8
1%
#1280000
0%
#1285000
b1 <
b11 8
1%
#1290000
0%
#1295000
b10 <
b1 8
b100110 "
b100110 9
1%
#1300000
0%
#1305000
b11 <
b10 8
1%
#1310000
0%
#1315000
b1 <
b11 8
1%
#1320000
0%
#1325000
b10 <
b1 8
b100111 "
b100111 9
1%
#1330000
0%
#1335000
b11 <
b10 8
1%
#1340000
0%
#1345000
b1 <
b11 8
1%
#1350000
0%
#1355000
b10 <
b1 8
b101000 "
b101000 9
1%
#1360000
0%
#1365000
b11 <
b10 8
1%
#1370000
0%
#1375000
b1 <
b11 8
1%
#1380000
0%
#1385000
b10 <
b1 8
b101001 "
b101001 9
1%
#1390000
0%
#1395000
b11 <
b10 8
1%
#1400000
0%
#1405000
b1 <
b11 8
1%
#1410000
0%
#1415000
b10 <
b1 8
b101010 "
b101010 9
1%
#1420000
0%
#1425000
b11 <
b10 8
1%
#1430000
0%
#1435000
b1 <
b11 8
1%
#1440000
0%
#1445000
b10 <
b1 8
b101011 "
b101011 9
1%
#1450000
0%
#1455000
b11 <
b10 8
1%
#1460000
0%
#1465000
b1 <
b11 8
1%
#1470000
0%
#1475000
b10 <
b1 8
b101100 "
b101100 9
1%
#1480000
0%
#1485000
b11 <
b10 8
1%
#1490000
0%
#1495000
b1 <
b11 8
1%
#1500000
0%
#1505000
b10 <
b1 8
b101101 "
b101101 9
1%
#1510000
0%
#1515000
b11 <
b10 8
1%
#1520000
0%
#1525000
b1 <
b11 8
1%
#1530000
0%
#1535000
b10 <
b1 8
b101110 "
b101110 9
1%
#1540000
0%
#1545000
b11 <
b10 8
1%
#1550000
0%
#1555000
b1 <
b11 8
1%
#1560000
0%
#1565000
b10 <
b1 8
b101111 "
b101111 9
1%
#1570000
0%
#1575000
b11 <
b10 8
1%
#1580000
0%
#1585000
b1 <
b11 8
1%
#1590000
0%
#1595000
b10 <
b1 8
b110000 "
b110000 9
1%
#1600000
0%
#1605000
b11 <
b10 8
1%
#1610000
0%
#1615000
b1 <
b11 8
1%
#1620000
0%
#1625000
b10 <
b1 8
b110001 "
b110001 9
1%
#1630000
0%
#1635000
b11 <
b10 8
1%
#1640000
0%
#1645000
b1 <
b11 8
1%
#1650000
0%
#1655000
b10 <
b1 8
b110010 "
b110010 9
1%
#1660000
0%
#1665000
b11 <
b10 8
1%
#1670000
0%
#1675000
b1 <
b11 8
1%
#1680000
0%
#1685000
b10 <
b1 8
b110011 "
b110011 9
1%
#1690000
0%
#1695000
b11 <
b10 8
1%
#1700000
0%
#1705000
b1 <
b11 8
1%
#1710000
0%
#1715000
b10 <
b1 8
b110100 "
b110100 9
1%
#1720000
0%
#1725000
b11 <
b10 8
1%
#1730000
0%
#1735000
b1 <
b11 8
1%
#1740000
0%
#1745000
b10 <
b1 8
b110101 "
b110101 9
1%
#1750000
0%
#1755000
b11 <
b10 8
1%
#1760000
0%
#1765000
b1 <
b11 8
1%
#1770000
0%
#1775000
b10 <
b1 8
b110110 "
b110110 9
1%
#1780000
0%
#1785000
b11 <
b10 8
1%
#1790000
0%
#1795000
b1 <
b11 8
1%
#1800000
0%
#1805000
b10 <
b1 8
b110111 "
b110111 9
1%
#1810000
0%
#1815000
b11 <
b10 8
1%
#1820000
0%
#1825000
b1 <
b11 8
1%
#1830000
0%
#1835000
b10 <
b1 8
b111000 "
b111000 9
1%
#1840000
0%
#1845000
b11 <
b10 8
1%
#1850000
0%
#1855000
b1 <
b11 8
1%
#1860000
0%
#1865000
b10 <
b1 8
b111001 "
b111001 9
1%
#1870000
0%
#1875000
b11 <
b10 8
1%
#1880000
0%
#1885000
b1 <
b11 8
1%
#1890000
0%
#1895000
b10 <
b1 8
b111010 "
b111010 9
1%
#1900000
0%
#1905000
b11 <
b10 8
1%
#1910000
0%
#1915000
b1 <
b11 8
1%
#1920000
0%
#1925000
b10 <
b1 8
b111011 "
b111011 9
1%
#1930000
0%
#1935000
b11 <
b10 8
1%
#1940000
0%
#1945000
b1 <
b11 8
1%
#1950000
0%
#1955000
b10 <
b1 8
b111100 "
b111100 9
1%
#1960000
0%
#1965000
b11 <
b10 8
1%
#1970000
0%
#1975000
b1 <
b11 8
1%
#1980000
0%
#1985000
b10 <
b1 8
b111101 "
b111101 9
1%
#1990000
0%
#1995000
b11 <
b10 8
1%
#2000000
0%
#2005000
b1 <
b11 8
1%
#2010000
0%
#2015000
b10 <
b1 8
b111110 "
b111110 9
1%
#2020000
0%
#2025000
b11 <
b10 8
1%
#2030000
0%
#2035000
b1 <
b11 8
1%
#2040000
0%
#2045000
b10 <
b1 8
b111111 "
b111111 9
1%
#2050000
0%
#2055000
b11 <
b10 8
1%
#2060000
0%
#2065000
b1 <
b11 8
1%
#2070000
0%
#2075000
b10 <
b1 8
b1000000 "
b1000000 9
1%
#2080000
0%
#2085000
b11 <
b10 8
1%
#2090000
0%
#2095000
b1 <
b11 8
1%
#2100000
0%
#2105000
b10 <
b1 8
b1000001 "
b1000001 9
1%
#2110000
0%
#2115000
b11 <
b10 8
1%
#2120000
0%
#2125000
b1 <
b11 8
1%
#2130000
0%
#2135000
b10 <
b1 8
b1000010 "
b1000010 9
1%
#2140000
0%
#2145000
b11 <
b10 8
1%
#2150000
0%
#2155000
b1 <
b11 8
1%
#2160000
0%
#2165000
b10 <
b1 8
b1000011 "
b1000011 9
1%
#2170000
0%
#2175000
b11 <
b10 8
1%
#2180000
0%
#2185000
b1 <
b11 8
1%
#2190000
0%
#2195000
b10 <
b1 8
b1000100 "
b1000100 9
1%
#2200000
0%
#2205000
b11 <
b10 8
1%
#2210000
0%
#2215000
b1 <
b11 8
1%
#2220000
0%
#2225000
b10 <
b1 8
b1000101 "
b1000101 9
1%
#2230000
0%
#2235000
b11 <
b10 8
1%
#2240000
0%
#2245000
b1 <
b11 8
1%
#2250000
0%
#2255000
b10 <
b1 8
b1000110 "
b1000110 9
1%
#2260000
0%
#2265000
b11 <
b10 8
1%
#2270000
0%
#2275000
b1 <
b11 8
1%
#2280000
0%
#2285000
b10 <
b1 8
b1000111 "
b1000111 9
1%
#2290000
0%
#2295000
b11 <
b10 8
1%
#2300000
0%
#2305000
b1 <
b11 8
1%
#2310000
0%
#2315000
b10 <
b1 8
b1001000 "
b1001000 9
1%
#2320000
0%
#2325000
b11 <
b10 8
1%
#2330000
0%
#2335000
b1 <
b11 8
1%
#2340000
0%
#2345000
b10 <
b1 8
b1001001 "
b1001001 9
1%
#2350000
0%
#2355000
b11 <
b10 8
1%
#2360000
0%
#2365000
b1 <
b11 8
1%
#2370000
0%
#2375000
b10 <
b1 8
b1001010 "
b1001010 9
1%
#2380000
0%
#2385000
b11 <
b10 8
1%
#2390000
0%
#2395000
b1 <
b11 8
1%
#2400000
0%
#2405000
b10 <
b1 8
b1001011 "
b1001011 9
1%
#2410000
0%
#2415000
b11 <
b10 8
1%
#2420000
0%
#2425000
b1 <
b11 8
1%
#2430000
0%
#2435000
b10 <
b1 8
b1001100 "
b1001100 9
1%
#2440000
0%
#2445000
b11 <
b10 8
1%
#2450000
0%
#2455000
b1 <
b11 8
1%
#2460000
0%
#2465000
b10 <
b1 8
b1001101 "
b1001101 9
1%
#2470000
0%
#2475000
b11 <
b10 8
1%
#2480000
0%
#2485000
b1 <
b11 8
1%
#2490000
0%
#2495000
b10 <
b1 8
b1001110 "
b1001110 9
1%
#2500000
0%
#2505000
b11 <
b10 8
1%
#2510000
0%
#2515000
b1 <
b11 8
1%
#2520000
0%
#2525000
b10 <
b1 8
b1001111 "
b1001111 9
1%
#2530000
0%
#2535000
b11 <
b10 8
1%
#2540000
0%
#2545000
b1 <
b11 8
1%
#2550000
0%
#2555000
b10 <
b1 8
b1010000 "
b1010000 9
1%
#2560000
0%
#2565000
b11 <
b10 8
1%
#2570000
0%
#2575000
b1 <
b11 8
1%
#2580000
0%
#2585000
b10 <
b1 8
b1010001 "
b1010001 9
1%
#2590000
0%
#2595000
b11 <
b10 8
1%
#2600000
0%
#2605000
b1 <
b11 8
1%
#2610000
0%
#2615000
b10 <
b1 8
b1010010 "
b1010010 9
1%
#2620000
0%
#2625000
b11 <
b10 8
1%
#2630000
0%
#2635000
b1 <
b11 8
1%
#2640000
0%
#2645000
b10 <
b1 8
b1010011 "
b1010011 9
1%
#2650000
0%
#2655000
b11 <
b10 8
1%
#2660000
0%
#2665000
b1 <
b11 8
1%
#2670000
0%
#2675000
b10 <
b1 8
b1010100 "
b1010100 9
1%
#2680000
0%
#2685000
b11 <
b10 8
1%
#2690000
0%
#2695000
b1 <
b11 8
1%
#2700000
0%
#2705000
b10 <
b1 8
b1010101 "
b1010101 9
1%
#2710000
0%
#2715000
b11 <
b10 8
1%
#2720000
0%
#2725000
b1 <
b11 8
1%
#2730000
0%
#2735000
b10 <
b1 8
b1010110 "
b1010110 9
1%
#2740000
0%
#2745000
b11 <
b10 8
1%
#2750000
0%
#2755000
b1 <
b11 8
1%
#2760000
0%
#2765000
b10 <
b1 8
b1010111 "
b1010111 9
1%
#2770000
0%
#2775000
b11 <
b10 8
1%
#2780000
0%
#2785000
b1 <
b11 8
1%
#2790000
0%
#2795000
b10 <
b1 8
b1011000 "
b1011000 9
1%
#2800000
0%
#2805000
b11 <
b10 8
1%
#2810000
0%
#2815000
b1 <
b11 8
1%
#2820000
0%
#2825000
b10 <
b1 8
b1011001 "
b1011001 9
1%
#2830000
0%
#2835000
b11 <
b10 8
1%
#2840000
0%
#2845000
b1 <
b11 8
1%
#2850000
0%
#2855000
b10 <
b1 8
b1011010 "
b1011010 9
1%
#2860000
0%
#2865000
b11 <
b10 8
1%
#2870000
0%
#2875000
b1 <
b11 8
1%
#2880000
0%
#2885000
b10 <
b1 8
b1011011 "
b1011011 9
1%
#2890000
0%
#2895000
b11 <
b10 8
1%
#2900000
0%
#2905000
b1 <
b11 8
1%
#2910000
0%
#2915000
b10 <
b1 8
b1011100 "
b1011100 9
1%
#2920000
0%
#2925000
b11 <
b10 8
1%
#2930000
0%
#2935000
b1 <
b11 8
1%
#2940000
0%
#2945000
b10 <
b1 8
b1011101 "
b1011101 9
1%
#2950000
0%
#2955000
b11 <
b10 8
1%
#2960000
0%
#2965000
b1 <
b11 8
1%
#2970000
0%
#2975000
b10 <
b1 8
b1011110 "
b1011110 9
1%
#2980000
0%
#2985000
b11 <
b10 8
1%
#2990000
0%
#2995000
b1 <
b11 8
1%
#3000000
0%
#3005000
b10 <
b1 8
b1011111 "
b1011111 9
1%
#3010000
0%
#3015000
b11 <
b10 8
1%
#3020000
0%
#3025000
b1 <
b11 8
1%
#3030000
0%
#3035000
b10 <
b1 8
b1100000 "
b1100000 9
1%
#3040000
0%
#3045000
b11 <
b10 8
1%
#3050000
0%
#3055000
b1 <
b11 8
1%
#3060000
0%
#3065000
b10 <
b1 8
b1100001 "
b1100001 9
1%
#3070000
0%
#3075000
b11 <
b10 8
1%
#3080000
0%
#3085000
b1 <
b11 8
1%
#3090000
0%
#3095000
b10 <
b1 8
b1100010 "
b1100010 9
1%
#3100000
0%
#3105000
b11 <
b10 8
1%
#3110000
0%
#3115000
b1 <
b11 8
1%
#3120000
0%
#3125000
b10 <
b1 8
b1100011 "
b1100011 9
1%
#3130000
0%
#3135000
b11 <
b10 8
1%
#3140000
0%
#3145000
b1 <
b11 8
1%
#3150000
0%
#3155000
b10 <
b1 8
b1100100 "
b1100100 9
1%
#3160000
0%
#3165000
b11 <
b10 8
1%
#3170000
0%
#3175000
b1 <
b11 8
1%
#3180000
0%
#3185000
b10 <
b1 8
b1100101 "
b1100101 9
1%
#3190000
0%
#3195000
b11 <
b10 8
1%
#3200000
0%
#3205000
b1 <
b11 8
1%
#3210000
0%
#3215000
b10 <
b1 8
b1100110 "
b1100110 9
1%
#3220000
0%
#3225000
b11 <
b10 8
1%
#3230000
0%
#3235000
b1 <
b11 8
1%
#3240000
0%
#3245000
b10 <
b1 8
b1100111 "
b1100111 9
1%
#3250000
0%
#3255000
b11 <
b10 8
1%
#3260000
0%
#3265000
b1 <
b11 8
1%
#3270000
0%
#3275000
b10 <
b1 8
b1101000 "
b1101000 9
1%
#3280000
0%
#3285000
b11 <
b10 8
1%
#3290000
0%
#3295000
b1 <
b11 8
1%
#3300000
0%
#3305000
b10 <
b1 8
b1101001 "
b1101001 9
1%
#3310000
0%
#3315000
b11 <
b10 8
1%
#3320000
0%
#3325000
b1 <
b11 8
1%
#3330000
0%
#3335000
b10 <
b1 8
b1101010 "
b1101010 9
1%
#3340000
0%
#3345000
b11 <
b10 8
1%
#3350000
0%
#3355000
b1 <
b11 8
1%
#3360000
0%
#3365000
b10 <
b1 8
b1101011 "
b1101011 9
1%
#3370000
0%
#3375000
b11 <
b10 8
1%
#3380000
0%
#3385000
b1 <
b11 8
1%
#3390000
0%
#3395000
b10 <
b1 8
b1101100 "
b1101100 9
1%
#3400000
0%
#3405000
b11 <
b10 8
1%
#3410000
0%
#3415000
b1 <
b11 8
1%
#3420000
0%
#3425000
b10 <
b1 8
b1101101 "
b1101101 9
1%
#3430000
0%
#3435000
b11 <
b10 8
1%
#3440000
0%
#3445000
b1 <
b11 8
1%
#3450000
0%
#3455000
b10 <
b1 8
b1101110 "
b1101110 9
1%
#3460000
0%
#3465000
b11 <
b10 8
1%
#3470000
0%
#3475000
b1 <
b11 8
1%
#3480000
0%
#3485000
b10 <
b1 8
b1101111 "
b1101111 9
1%
#3490000
0%
#3495000
b11 <
b10 8
1%
#3500000
0%
#3505000
b1 <
b11 8
1%
#3510000
0%
#3515000
b10 <
b1 8
b1110000 "
b1110000 9
1%
#3520000
0%
#3525000
b11 <
b10 8
1%
#3530000
0%
#3535000
b1 <
b11 8
1%
#3540000
0%
#3545000
b10 <
b1 8
b1110001 "
b1110001 9
1%
#3550000
0%
#3555000
b11 <
b10 8
1%
#3560000
0%
#3565000
b1 <
b11 8
1%
#3570000
0%
#3575000
b10 <
b1 8
b1110010 "
b1110010 9
1%
#3580000
0%
